BUILD.md
LICENSE
MANIFEST.in
README.md
setup.cfg
setup.py
OrangePi.ky040.egg-info/PKG-INFO
OrangePi.ky040.egg-info/SOURCES.txt
OrangePi.ky040.egg-info/dependency_links.txt
OrangePi.ky040.egg-info/requires.txt
OrangePi.ky040.egg-info/top_level.txt
OrangePi_ky040/__init__.py
OrangePi_ky040/pyky040.py
OrangePi_ky040/pyky040_test.py