Metadata-Version: 2.1
Name: OrangePi.ky040
Version: 0.2.0
Summary: High-level interface for the KY040 rotary encoder and switch.
Home-page: https://github.com/sonocotta/orangepi-ky040
Author: Andriy Malyshenko
Author-email: anriy@sonocotta.com
Project-URL: Bug Reports, https://github.com/sonocotta/orangepi-ky040/issues
Project-URL: Source, https://github.com/sonocotta/orangepi-ky040
Keywords: keyes rotary encoder switch ky040
Provides-Extra: device
License-File: LICENSE
